word_count.py
word_count-0.1.0.dist-info/RECORD
word_count-0.1.0.dist-info/DESCRIPTION.rst
word_count-0.1.0.dist-info/top_level.txt
word_count-0.1.0.dist-info/METADATA
word_count-0.1.0.dist-info/WHEEL
word_count-0.1.0.dist-info/metadata.json
